setup.py
alfred5/__init__.py
alfred5/client.py
alfred5/errors.py
alfred5/models.py
alfred5/icons/download.png
alfred5/icons/error.png
tests/__init__.py
tests/test_snippets.py
alfred5-1.1.6.dist-info/LICENSE
alfred5-1.1.6.dist-info/METADATA
alfred5-1.1.6.dist-info/WHEEL
alfred5-1.1.6.dist-info/top_level.txt
alfred5-1.1.6.dist-info/RECORD
