Metadata-Version: 2.1
Name: alfred5
Version: 1.1.6
Summary: Simple python wrapper for alfred5 workflow / snippets
Home-page: https://github.com/yedhrab/alfred5
Author: Yunus Emre Ak
Author-email: yemreak.com@gmail.com
License: Apache Software License 2.0
Project-URL: Source, https://github.com/yedhrab/alfred5/
Project-URL: Changelog, https://github.com/yedhrab/alfred5/releases
Project-URL: Issue Tracker, https://github.com/yedhrab/alfred5/issues
Keywords: alfred,alfred5,workflow,snippets,alfred-workflows,alfred-snippets
Classifier: Development Status :: 5 - Production/Stable
Classifier: Intended Audience :: Developers
Classifier: License :: OSI Approved :: Apache Software License
Classifier: Operating System :: OS Independent
Classifier: Programming Language :: Python :: 3.9
Classifier: Programming Language :: Python :: 3.10
Classifier: Programming Language :: Python :: 3.11
Classifier: Topic :: Utilities
Requires-Python: >=3.9.6
License-File: LICENSE
Requires-Dist: aiohttp (==3.8.4)
Requires-Dist: PyYAML (==6.0)
Provides-Extra: dev
Requires-Dist: black (==23.3.0) ; extra == 'dev'
Requires-Dist: autoflake (==2.0.2) ; extra == 'dev'
Requires-Dist: pytest (==7.3.0) ; extra == 'dev'
Requires-Dist: pytest-asyncio (==0.21.0) ; extra == 'dev'
